dj_crt_mgr/__init__.py
dj_crt_mgr/admin.py
dj_crt_mgr/apps.py
dj_crt_mgr/forms.py
dj_crt_mgr/models.py
dj_crt_mgr/signals.py
dj_crt_mgr/utils.py
dj_crt_mgr/version.py
dj_crt_mgr/views.py
dj_crt_mgr/migrations/0001_initial.py
dj_crt_mgr/migrations/__init__.py
dj_crt_mgr/templates/admin/dj_crt_mgr/httpusercertmapper/change_form.html
dj_crt_mgr/templates/admin/dj_crt_mgr/ldapusercertmapper/change_form.html
dj_crt_mgr-0.4.0.dist-info/LICENSE
dj_crt_mgr-0.4.0.dist-info/METADATA
dj_crt_mgr-0.4.0.dist-info/WHEEL
dj_crt_mgr-0.4.0.dist-info/top_level.txt
dj_crt_mgr-0.4.0.dist-info/RECORD
